{"type": "FeatureCollection", "features": [{"id": "0", "type": "Feature", "properties": {"bbox_north": 21.464547, "bbox_south": 21.144547, "bbox_east": -157.695676, "bbox_west": -158.015676, "place_id": 32733937, "osm_type": "node", "osm_id": 21442033, "lat": 21.304547, "lon": -157.855676, "class": "place", "type": "city", "place_rank": 16, "importance": 0.6200364125622267, "addresstype": "city", "name": "Honolulu", "display_name": "Honolulu, Honolulu County, Hawaii, 96813, United States"}, "geometry": {"type": "Point", "coordinates": [-157.855676, 21.304547]}}]}